sheet2csv/__init__.py
sheet2csv/__main__.py
sheet2csv-1.0.7.dist-info/LICENSE.txt
sheet2csv-1.0.7.dist-info/METADATA
sheet2csv-1.0.7.dist-info/WHEEL
sheet2csv-1.0.7.dist-info/top_level.txt
sheet2csv-1.0.7.dist-info/RECORD
