Metadata-Version: 2.1
Name: sheet2csv
Version: 1.0.7
Summary: A package to export Google Sheet to CSV via API
Home-page: https://github.com/sledilnik/sheet2csv
Author: sledilnik.org
Author-email: info@sledilnik.org
Project-URL: Bug Tracker, https://github.com/sledilnik/sheet2csv/issues
Classifier: Programming Language :: Python :: 3
Classifier: License :: OSI Approved :: MIT License
Classifier: Operating System :: OS Independent
Requires-Python: >=3.6
License-File: LICENSE.txt
Requires-Dist: google-api-python-client
Requires-Dist: google-auth-httplib2
Requires-Dist: google-auth-oauthlib
Requires-Dist: python-dateutil
